slack.py-0.0.2.data/scripts/main.py
slack.py-0.0.2.dist-info/DESCRIPTION.rst
slack.py-0.0.2.dist-info/METADATA
slack.py-0.0.2.dist-info/RECORD
slack.py-0.0.2.dist-info/WHEEL
slack.py-0.0.2.dist-info/entry_points.txt
slack.py-0.0.2.dist-info/metadata.json
slack.py-0.0.2.dist-info/top_level.txt
slack.py-0.0.2.dist-info/zip-safe
slack_cli/__init__.py
slack_cli/api.py
slack_cli/cmd.py
slack_cli/utils.py
